{
    "22": "Helsinki, Finland (3) (Hetzner)",
    "24": "Helsinki, Finland (5) (Hetzner)",
    "27": "Nuremberg, Germany (2) (Hetzner)",
    "28": "Nuremberg, Germany (1) (Hetzner)",
    "30": "Nuremberg, Germany (3) (Hetzner)",
    "31": "Nuremberg, Germany (4) (Hetzner)",
    "33": "Bari, Italy (GARR)",
    "34": "Bologna, Italy (GARR)",
    "35": "Roma, Italy (GARR)",
    "43": "Nottingham, England (LayerIP)",
    "46": "Nuremberg, Germany (6) (Hetzner)",
    "49": "London, England (Clouvider)",
    "50": "Frankfurt, Germany (Clouvider)",
    "51": "Amsterdam, Netherlands (Clouvider)",
    "52": "New York, United States (2) (Clouvider)",
    "53": "Atlanta, United States (Clouvider)",
    "54": "Los Angeles, United States (1) (Clouvider)",
    "68": "Singapore (Salvatore Cahyo)",
    "69": "Vilnius, Lithuania (RackRay)",
    "70": "Johannesburg, South Africa (Host Africa)",
    "74": "Poznan, Poland (INEA)",
    "75": "Bangalore, India (DigitalOcean)",
    "76": "Tehran, Iran (Fanava)",
    "77": "Ghom, Iran (Amin IDC)",
    "78": "Virginia, United States, OVH",
    "79": "Prague, Czech Republic (CESNET)",
    "80": "Tehran, Iran (Faraso)",
    "82": "Tokyo, Japan (A573)",
    "85": "Prague, Czech Republic (Turris)",
    "86": "Frankfurt, Germany (FRA01)",
    "87": "Serbia (SOX)",
    "90": "Las Vegas, USA (Sharktech)",
    "91": "Los Angeles, USA (Sharktech)",
    "92": "Denver, USA (Sharktech)",
    "93": "Chicago, USA (Sharktech)",
    "94": "Amsterdam, Netherlands (Sharktech)",
    "95": "Ohio, USA (Rust backend)",
    "98": "Bucharest, Romania (ByteShield)"
}